Workbook

Sheet Resumen
A1: Mis finanzas
A2: Última actualización:
A3: La llena tu bot de Telegram automáticamente. Las pestañas de datos no se editan a mano; las correcciones se hacen por el bot (/borrar, /cat…).
A5: Inicio del mes | B5: =DATE(YEAR(TODAY()),MONTH(TODAY()),1) -> 46266
A6: Inicio de la semana (lunes) | B6: =TODAY()-WEEKDAY(TODAY(),3) -> 46286
A7: Indicador | B7: Valor
A8: Gastos del mes | B8: =SUMIFS(Movimientos!$C:$C,Movimientos!$B:$B,"Gasto",Movimientos!$A:$A,">="&$B$5) -> 0
A9: Ingresos del mes | B9: =SUMIFS(Movimientos!$C:$C,Movimientos!$B:$B,"Ingreso",Movimientos!$A:$A,">="&$B$5) -> 0
A10: Balance del mes | B10: =B9-B8 -> 0
A11: Gastos de esta semana | B11: =SUMIFS(Movimientos!$C:$C,Movimientos!$B:$B,"Gasto",Movimientos!$A:$A,">="&$B$6) -> 0
A12: Promedio diario (mes) | B12: =IFERROR(B8/DAY(TODAY()),0) -> 0
A13: Gastos del mes anterior | B13: =SUMIFS(Movimientos!$C:$C,Movimientos!$B:$B,"Gasto",Movimientos!$A:$A,">="&EDATE($B$5,-1),Movimientos!$A:$A,"<"&$B$5) -> 0
A14: Te deben | B14: =SUMIF(Deudas!$B:$B,">0") -> 0
A15: Debes | B15: =-SUMIF(Deudas!$B:$B,"<0") -> 0
A16: Ahorrado en metas | B16: =SUM(Metas!$C:$C) -> 0

Sheet Mensual
A1: Mes | B1: Ingresos (S/) | C1: Gastos (S/) | D1: Balance (S/) | E1: % gastado
A2: =EDATE(Resumen!$B$5,-11) -> 45931 | B2: =SUMIFS(Movimientos!$C:$C,Movimientos!$B:$B,"Ingreso",Movimientos!$A:$A,">="&A2,Movimientos!$A:$A,"<"&EDATE(A2,1)) -> 0 | C2: =SUMIFS(Movimientos!$C:$C,Movimientos!$B:$B,"Gasto",Movimientos!$A:$A,">="&A2,Movimientos!$A:$A,"<"&EDATE(A2,1)) -> 0 | D2: =B2-C2 -> 0 | E2: =IF(B2>0,C2/B2,"")
A3: =EDATE(Resumen!$B$5,-10) -> 45962 | B3: =SUMIFS(Movimientos!$C:$C,Movimientos!$B:$B,"Ingreso",Movimientos!$A:$A,">="&A3,Movimientos!$A:$A,"<"&EDATE(A3,1)) -> 0 | C3: =SUMIFS(Movimientos!$C:$C,Movimientos!$B:$B,"Gasto",Movimientos!$A:$A,">="&A3,Movimientos!$A:$A,"<"&EDATE(A3,1)) -> 0 | D3: =B3-C3 -> 0 | E3: =IF(B3>0,C3/B3,"")
A4: =EDATE(Resumen!$B$5,-9) -> 45992 | B4: =SUMIFS(Movimientos!$C:$C,Movimientos!$B:$B,"Ingreso",Movimientos!$A:$A,">="&A4,Movimientos!$A:$A,"<"&EDATE(A4,1)) -> 0 | C4: =SUMIFS(Movimientos!$C:$C,Movimientos!$B:$B,"Gasto",Movimientos!$A:$A,">="&A4,Movimientos!$A:$A,"<"&EDATE(A4,1)) -> 0 | D4: =B4-C4 -> 0 | E4: =IF(B4>0,C4/B4,"")
A5: =EDATE(Resumen!$B$5,-8) -> 46023 | B5: =SUMIFS(Movimientos!$C:$C,Movimientos!$B:$B,"Ingreso",Movimientos!$A:$A,">="&A5,Movimientos!$A:$A,"<"&EDATE(A5,1)) -> 0 | C5: =SUMIFS(Movimientos!$C:$C,Movimientos!$B:$B,"Gasto",Movimientos!$A:$A,">="&A5,Movimientos!$A:$A,"<"&EDATE(A5,1)) -> 0 | D5: =B5-C5 -> 0 | E5: =IF(B5>0,C5/B5,"")
A6: =EDATE(Resumen!$B$5,-7) -> 46054 | B6: =SUMIFS(Movimientos!$C:$C,Movimientos!$B:$B,"Ingreso",Movimientos!$A:$A,">="&A6,Movimientos!$A:$A,"<"&EDATE(A6,1)) -> 0 | C6: =SUMIFS(Movimientos!$C:$C,Movimientos!$B:$B,"Gasto",Movimientos!$A:$A,">="&A6,Movimientos!$A:$A,"<"&EDATE(A6,1)) -> 0 | D6: =B6-C6 -> 0 | E6: =IF(B6>0,C6/B6,"")
A7: =EDATE(Resumen!$B$5,-6) -> 46082 | B7: =SUMIFS(Movimientos!$C:$C,Movimientos!$B:$B,"Ingreso",Movimientos!$A:$A,">="&A7,Movimientos!$A:$A,"<"&EDATE(A7,1)) -> 0 | C7: =SUMIFS(Movimientos!$C:$C,Movimientos!$B:$B,"Gasto",Movimientos!$A:$A,">="&A7,Movimientos!$A:$A,"<"&EDATE(A7,1)) -> 0 | D7: =B7-C7 -> 0 | E7: =IF(B7>0,C7/B7,"")
A8: =EDATE(Resumen!$B$5,-5) -> 46113 | B8: =SUMIFS(Movimientos!$C:$C,Movimientos!$B:$B,"Ingreso",Movimientos!$A:$A,">="&A8,Movimientos!$A:$A,"<"&EDATE(A8,1)) -> 0 | C8: =SUMIFS(Movimientos!$C:$C,Movimientos!$B:$B,"Gasto",Movimientos!$A:$A,">="&A8,Movimientos!$A:$A,"<"&EDATE(A8,1)) -> 0 | D8: =B8-C8 -> 0 | E8: =IF(B8>0,C8/B8,"")
A9: =EDATE(Resumen!$B$5,-4) -> 46143 | B9: =SUMIFS(Movimientos!$C:$C,Movimientos!$B:$B,"Ingreso",Movimientos!$A:$A,">="&A9,Movimientos!$A:$A,"<"&EDATE(A9,1)) -> 0 | C9: =SUMIFS(Movimientos!$C:$C,Movimientos!$B:$B,"Gasto",Movimientos!$A:$A,">="&A9,Movimientos!$A:$A,"<"&EDATE(A9,1)) -> 0 | D9: =B9-C9 -> 0 | E9: =IF(B9>0,C9/B9,"")
A10: =EDATE(Resumen!$B$5,-3) -> 46174 | B10: =SUMIFS(Movimientos!$C:$C,Movimientos!$B:$B,"Ingreso",Movimientos!$A:$A,">="&A10,Movimientos!$A:$A,"<"&EDATE(A10,1)) -> 0 | C10: =SUMIFS(Movimientos!$C:$C,Movimientos!$B:$B,"Gasto",Movimientos!$A:$A,">="&A10,Movimientos!$A:$A,"<"&EDATE(A10,1)) -> 0 | D10: =B10-C10 -> 0 | E10: =IF(B10>0,C10/B10,"")
A11: =EDATE(Resumen!$B$5,-2) -> 46204 | B11: =SUMIFS(Movimientos!$C:$C,Movimientos!$B:$B,"Ingreso",Movimientos!$A:$A,">="&A11,Movimientos!$A:$A,"<"&EDATE(A11,1)) -> 0 | C11: =SUMIFS(Movimientos!$C:$C,Movimientos!$B:$B,"Gasto",Movimientos!$A:$A,">="&A11,Movimientos!$A:$A,"<"&EDATE(A11,1)) -> 0 | D11: =B11-C11 -> 0 | E11: =IF(B11>0,C11/B11,"")
A12: =EDATE(Resumen!$B$5,-1) -> 46235 | B12: =SUMIFS(Movimientos!$C:$C,Movimientos!$B:$B,"Ingreso",Movimientos!$A:$A,">="&A12,Movimientos!$A:$A,"<"&EDATE(A12,1)) -> 0 | C12: =SUMIFS(Movimientos!$C:$C,Movimientos!$B:$B,"Gasto",Movimientos!$A:$A,">="&A12,Movimientos!$A:$A,"<"&EDATE(A12,1)) -> 0 | D12: =B12-C12 -> 0 | E12: =IF(B12>0,C12/B12,"")
A13: =EDATE(Resumen!$B$5,0) -> 46266 | B13: =SUMIFS(Movimientos!$C:$C,Movimientos!$B:$B,"Ingreso",Movimientos!$A:$A,">="&A13,Movimientos!$A:$A,"<"&EDATE(A13,1)) -> 0 | C13: =SUMIFS(Movimientos!$C:$C,Movimientos!$B:$B,"Gasto",Movimientos!$A:$A,">="&A13,Movimientos!$A:$A,"<"&EDATE(A13,1)) -> 0 | D13: =B13-C13 -> 0 | E13: =IF(B13>0,C13/B13,"")
A14: Total 12 meses | B14: =SUM(B2:B13) -> 0 | C14: =SUM(C2:C13) -> 0 | D14: =SUM(D2:D13) -> 0

Sheet Semanal
A1: Semana (lunes) | B1: Ingresos (S/) | C1: Gastos (S/) | D1: Balance (S/)
A2: =Resumen!$B$6-7*11 -> 46209 | B2: =SUMIFS(Movimientos!$C:$C,Movimientos!$B:$B,"Ingreso",Movimientos!$A:$A,">="&A2,Movimientos!$A:$A,"<"&(A2+7)) -> 0 | C2: =SUMIFS(Movimientos!$C:$C,Movimientos!$B:$B,"Gasto",Movimientos!$A:$A,">="&A2,Movimientos!$A:$A,"<"&(A2+7)) -> 0 | D2: =B2-C2 -> 0
A3: =Resumen!$B$6-7*10 -> 46216 | B3: =SUMIFS(Movimientos!$C:$C,Movimientos!$B:$B,"Ingreso",Movimientos!$A:$A,">="&A3,Movimientos!$A:$A,"<"&(A3+7)) -> 0 | C3: =SUMIFS(Movimientos!$C:$C,Movimientos!$B:$B,"Gasto",Movimientos!$A:$A,">="&A3,Movimientos!$A:$A,"<"&(A3+7)) -> 0 | D3: =B3-C3 -> 0
A4: =Resumen!$B$6-7*9 -> 46223 | B4: =SUMIFS(Movimientos!$C:$C,Movimientos!$B:$B,"Ingreso",Movimientos!$A:$A,">="&A4,Movimientos!$A:$A,"<"&(A4+7)) -> 0 | C4: =SUMIFS(Movimientos!$C:$C,Movimientos!$B:$B,"Gasto",Movimientos!$A:$A,">="&A4,Movimientos!$A:$A,"<"&(A4+7)) -> 0 | D4: =B4-C4 -> 0
A5: =Resumen!$B$6-7*8 -> 46230 | B5: =SUMIFS(Movimientos!$C:$C,Movimientos!$B:$B,"Ingreso",Movimientos!$A:$A,">="&A5,Movimientos!$A:$A,"<"&(A5+7)) -> 0 | C5: =SUMIFS(Movimientos!$C:$C,Movimientos!$B:$B,"Gasto",Movimientos!$A:$A,">="&A5,Movimientos!$A:$A,"<"&(A5+7)) -> 0 | D5: =B5-C5 -> 0
A6: =Resumen!$B$6-7*7 -> 46237 | B6: =SUMIFS(Movimientos!$C:$C,Movimientos!$B:$B,"Ingreso",Movimientos!$A:$A,">="&A6,Movimientos!$A:$A,"<"&(A6+7)) -> 0 | C6: =SUMIFS(Movimientos!$C:$C,Movimientos!$B:$B,"Gasto",Movimientos!$A:$A,">="&A6,Movimientos!$A:$A,"<"&(A6+7)) -> 0 | D6: =B6-C6 -> 0
A7: =Resumen!$B$6-7*6 -> 46244 | B7: =SUMIFS(Movimientos!$C:$C,Movimientos!$B:$B,"Ingreso",Movimientos!$A:$A,">="&A7,Movimientos!$A:$A,"<"&(A7+7)) -> 0 | C7: =SUMIFS(Movimientos!$C:$C,Movimientos!$B:$B,"Gasto",Movimientos!$A:$A,">="&A7,Movimientos!$A:$A,"<"&(A7+7)) -> 0 | D7: =B7-C7 -> 0
A8: =Resumen!$B$6-7*5 -> 46251 | B8: =SUMIFS(Movimientos!$C:$C,Movimientos!$B:$B,"Ingreso",Movimientos!$A:$A,">="&A8,Movimientos!$A:$A,"<"&(A8+7)) -> 0 | C8: =SUMIFS(Movimientos!$C:$C,Movimientos!$B:$B,"Gasto",Movimientos!$A:$A,">="&A8,Movimientos!$A:$A,"<"&(A8+7)) -> 0 | D8: =B8-C8 -> 0
A9: =Resumen!$B$6-7*4 -> 46258 | B9: =SUMIFS(Movimientos!$C:$C,Movimientos!$B:$B,"Ingreso",Movimientos!$A:$A,">="&A9,Movimientos!$A:$A,"<"&(A9+7)) -> 0 | C9: =SUMIFS(Movimientos!$C:$C,Movimientos!$B:$B,"Gasto",Movimientos!$A:$A,">="&A9,Movimientos!$A:$A,"<"&(A9+7)) -> 0 | D9: =B9-C9 -> 0
A10: =Resumen!$B$6-7*3 -> 46265 | B10: =SUMIFS(Movimientos!$C:$C,Movimientos!$B:$B,"Ingreso",Movimientos!$A:$A,">="&A10,Movimientos!$A:$A,"<"&(A10+7)) -> 0 | C10: =SUMIFS(Movimientos!$C:$C,Movimientos!$B:$B,"Gasto",Movimientos!$A:$A,">="&A10,Movimientos!$A:$A,"<"&(A10+7)) -> 0 | D10: =B10-C10 -> 0
A11: =Resumen!$B$6-7*2 -> 46272 | B11: =SUMIFS(Movimientos!$C:$C,Movimientos!$B:$B,"Ingreso",Movimientos!$A:$A,">="&A11,Movimientos!$A:$A,"<"&(A11+7)) -> 0 | C11: =SUMIFS(Movimientos!$C:$C,Movimientos!$B:$B,"Gasto",Movimientos!$A:$A,">="&A11,Movimientos!$A:$A,"<"&(A11+7)) -> 0 | D11: =B11-C11 -> 0
A12: =Resumen!$B$6-7*1 -> 46279 | B12: =SUMIFS(Movimientos!$C:$C,Movimientos!$B:$B,"Ingreso",Movimientos!$A:$A,">="&A12,Movimientos!$A:$A,"<"&(A12+7)) -> 0 | C12: =SUMIFS(Movimientos!$C:$C,Movimientos!$B:$B,"Gasto",Movimientos!$A:$A,">="&A12,Movimientos!$A:$A,"<"&(A12+7)) -> 0 | D12: =B12-C12 -> 0
A13: =Resumen!$B$6-7*0 -> 46286 | B13: =SUMIFS(Movimientos!$C:$C,Movimientos!$B:$B,"Ingreso",Movimientos!$A:$A,">="&A13,Movimientos!$A:$A,"<"&(A13+7)) -> 0 | C13: =SUMIFS(Movimientos!$C:$C,Movimientos!$B:$B,"Gasto",Movimientos!$A:$A,">="&A13,Movimientos!$A:$A,"<"&(A13+7)) -> 0 | D13: =B13-C13 -> 0
A14: Promedio semanal | C14: =AVERAGE(C2:C13) -> 0

Sheet Categorías
A1: Categoría | B1: Gasto del mes (S/) | C1: Presupuesto (S/) | D1: % usado | E1: Te queda (S/) | F1: Mes anterior (S/) | G1: vs mes anterior
A2: Comida | B2: =SUMIFS(Movimientos!$C:$C,Movimientos!$B:$B,"Gasto",Movimientos!$D:$D,A2,Movimientos!$A:$A,">="&Resumen!$B$5) -> 0 | C2: =IFERROR(INDEX(Presupuestos!$B:$B,MATCH(A2,Presupuestos!$A:$A,0)),0) -> 0 | D2: =IF(C2>0,B2/C2,"") | E2: =IF(C2>0,C2-B2,"") | F2: =SUMIFS(Movimientos!$C:$C,Movimientos!$B:$B,"Gasto",Movimientos!$D:$D,A2,Movimientos!$A:$A,">="&EDATE(Resumen!$B$5,-1),Movimientos!$A:$A,"<"&Resumen!$B$5) -> 0 | G2: =IF(F2>0,B2/F2-1,"")
A3: Transporte | B3: =SUMIFS(Movimientos!$C:$C,Movimientos!$B:$B,"Gasto",Movimientos!$D:$D,A3,Movimientos!$A:$A,">="&Resumen!$B$5) -> 0 | C3: =IFERROR(INDEX(Presupuestos!$B:$B,MATCH(A3,Presupuestos!$A:$A,0)),0) -> 0 | D3: =IF(C3>0,B3/C3,"") | E3: =IF(C3>0,C3-B3,"") | F3: =SUMIFS(Movimientos!$C:$C,Movimientos!$B:$B,"Gasto",Movimientos!$D:$D,A3,Movimientos!$A:$A,">="&EDATE(Resumen!$B$5,-1),Movimientos!$A:$A,"<"&Resumen!$B$5) -> 0 | G3: =IF(F3>0,B3/F3-1,"")
A4: Ocio | B4: =SUMIFS(Movimientos!$C:$C,Movimientos!$B:$B,"Gasto",Movimientos!$D:$D,A4,Movimientos!$A:$A,">="&Resumen!$B$5) -> 0 | C4: =IFERROR(INDEX(Presupuestos!$B:$B,MATCH(A4,Presupuestos!$A:$A,0)),0) -> 0 | D4: =IF(C4>0,B4/C4,"") | E4: =IF(C4>0,C4-B4,"") | F4: =SUMIFS(Movimientos!$C:$C,Movimientos!$B:$B,"Gasto",Movimientos!$D:$D,A4,Movimientos!$A:$A,">="&EDATE(Resumen!$B$5,-1),Movimientos!$A:$A,"<"&Resumen!$B$5) -> 0 | G4: =IF(F4>0,B4/F4-1,"")
A5: Compras | B5: =SUMIFS(Movimientos!$C:$C,Movimientos!$B:$B,"Gasto",Movimientos!$D:$D,A5,Movimientos!$A:$A,">="&Resumen!$B$5) -> 0 | C5: =IFERROR(INDEX(Presupuestos!$B:$B,MATCH(A5,Presupuestos!$A:$A,0)),0) -> 0 | D5: =IF(C5>0,B5/C5,"") | E5: =IF(C5>0,C5-B5,"") | F5: =SUMIFS(Movimientos!$C:$C,Movimientos!$B:$B,"Gasto",Movimientos!$D:$D,A5,Movimientos!$A:$A,">="&EDATE(Resumen!$B$5,-1),Movimientos!$A:$A,"<"&Resumen!$B$5) -> 0 | G5: =IF(F5>0,B5/F5-1,"")
A6: Salud | B6: =SUMIFS(Movimientos!$C:$C,Movimientos!$B:$B,"Gasto",Movimientos!$D:$D,A6,Movimientos!$A:$A,">="&Resumen!$B$5) -> 0 | C6: =IFERROR(INDEX(Presupuestos!$B:$B,MATCH(A6,Presupuestos!$A:$A,0)),0) -> 0 | D6: =IF(C6>0,B6/C6,"") | E6: =IF(C6>0,C6-B6,"") | F6: =SUMIFS(Movimientos!$C:$C,Movimientos!$B:$B,"Gasto",Movimientos!$D:$D,A6,Movimientos!$A:$A,">="&EDATE(Resumen!$B$5,-1),Movimientos!$A:$A,"<"&Resumen!$B$5) -> 0 | G6: =IF(F6>0,B6/F6-1,"")
A7: Educación | B7: =SUMIFS(Movimientos!$C:$C,Movimientos!$B:$B,"Gasto",Movimientos!$D:$D,A7,Movimientos!$A:$A,">="&Resumen!$B$5) -> 0 | C7: =IFERROR(INDEX(Presupuestos!$B:$B,MATCH(A7,Presupuestos!$A:$A,0)),0) -> 0 | D7: =IF(C7>0,B7/C7,"") | E7: =IF(C7>0,C7-B7,"") | F7: =SUMIFS(Movimientos!$C:$C,Movimientos!$B:$B,"Gasto",Movimientos!$D:$D,A7,Movimientos!$A:$A,">="&EDATE(Resumen!$B$5,-1),Movimientos!$A:$A,"<"&Resumen!$B$5) -> 0 | G7: =IF(F7>0,B7/F7-1,"")
A8: Servicios | B8: =SUMIFS(Movimientos!$C:$C,Movimientos!$B:$B,"Gasto",Movimientos!$D:$D,A8,Movimientos!$A:$A,">="&Resumen!$B$5) -> 0 | C8: =IFERROR(INDEX(Presupuestos!$B:$B,MATCH(A8,Presupuestos!$A:$A,0)),0) -> 0 | D8: =IF(C8>0,B8/C8,"") | E8: =IF(C8>0,C8-B8,"") | F8: =SUMIFS(Movimientos!$C:$C,Movimientos!$B:$B,"Gasto",Movimientos!$D:$D,A8,Movimientos!$A:$A,">="&EDATE(Resumen!$B$5,-1),Movimientos!$A:$A,"<"&Resumen!$B$5) -> 0 | G8: =IF(F8>0,B8/F8-1,"")
A9: Hogar | B9: =SUMIFS(Movimientos!$C:$C,Movimientos!$B:$B,"Gasto",Movimientos!$D:$D,A9,Movimientos!$A:$A,">="&Resumen!$B$5) -> 0 | C9: =IFERROR(INDEX(Presupuestos!$B:$B,MATCH(A9,Presupuestos!$A:$A,0)),0) -> 0 | D9: =IF(C9>0,B9/C9,"") | E9: =IF(C9>0,C9-B9,"") | F9: =SUMIFS(Movimientos!$C:$C,Movimientos!$B:$B,"Gasto",Movimientos!$D:$D,A9,Movimientos!$A:$A,">="&EDATE(Resumen!$B$5,-1),Movimientos!$A:$A,"<"&Resumen!$B$5) -> 0 | G9: =IF(F9>0,B9/F9-1,"")
A10: Otros | B10: =SUMIFS(Movimientos!$C:$C,Movimientos!$B:$B,"Gasto",Movimientos!$D:$D,A10,Movimientos!$A:$A,">="&Resumen!$B$5) -> 0 | C10: =IFERROR(INDEX(Presupuestos!$B:$B,MATCH(A10,Presupuestos!$A:$A,0)),0) -> 0 | D10: =IF(C10>0,B10/C10,"") | E10: =IF(C10>0,C10-B10,"") | F10: =SUMIFS(Movimientos!$C:$C,Movimientos!$B:$B,"Gasto",Movimientos!$D:$D,A10,Movimientos!$A:$A,">="&EDATE(Resumen!$B$5,-1),Movimientos!$A:$A,"<"&Resumen!$B$5) -> 0 | G10: =IF(F10>0,B10/F10-1,"")
A11: Total | B11: =SUM(B2:B10) -> 0 | C11: =SUM(C2:C10) -> 0 | F11: =SUM(F2:F10) -> 0

Sheet Movimientos
A1: Fecha | B1: Tipo | C1: Monto (S/) | D1: Categoría | E1: Descripción | F1: Método | G1: Semana (lunes)

Sheet Presupuestos
A1: Categoría | B1: Presupuesto mensual (S/)

Sheet Deudas
A1: Persona | B1: Saldo (S/) | C1: Estado | E1: Fecha | F1: Persona | G1: Monto (S/) | H1: Descripción

Sheet Metas
A1: Meta | B1: Objetivo (S/) | C1: Ahorrado (S/) | D1: Fecha límite | E1: Progreso | F1: Falta (S/) | G1: Ahorrar por mes (S/)
E2: =IF(A2="","",IFERROR(C2/B2,0)) | F2: =IF(A2="","",MAX(B2-C2,0)) | G2: =IF(OR(A2="",D2=""),"",IFERROR(F2/(DATEDIF(TODAY(),D2,"m")+1),F2))
E3: =IF(A3="","",IFERROR(C3/B3,0)) | F3: =IF(A3="","",MAX(B3-C3,0)) | G3: =IF(OR(A3="",D3=""),"",IFERROR(F3/(DATEDIF(TODAY(),D3,"m")+1),F3))
E4: =IF(A4="","",IFERROR(C4/B4,0)) | F4: =IF(A4="","",MAX(B4-C4,0)) | G4: =IF(OR(A4="",D4=""),"",IFERROR(F4/(DATEDIF(TODAY(),D4,"m")+1),F4))
E5: =IF(A5="","",IFERROR(C5/B5,0)) | F5: =IF(A5="","",MAX(B5-C5,0)) | G5: =IF(OR(A5="",D5=""),"",IFERROR(F5/(DATEDIF(TODAY(),D5,"m")+1),F5))
E6: =IF(A6="","",IFERROR(C6/B6,0)) | F6: =IF(A6="","",MAX(B6-C6,0)) | G6: =IF(OR(A6="",D6=""),"",IFERROR(F6/(DATEDIF(TODAY(),D6,"m")+1),F6))
E7: =IF(A7="","",IFERROR(C7/B7,0)) | F7: =IF(A7="","",MAX(B7-C7,0)) | G7: =IF(OR(A7="",D7=""),"",IFERROR(F7/(DATEDIF(TODAY(),D7,"m")+1),F7))
E8: =IF(A8="","",IFERROR(C8/B8,0)) | F8: =IF(A8="","",MAX(B8-C8,0)) | G8: =IF(OR(A8="",D8=""),"",IFERROR(F8/(DATEDIF(TODAY(),D8,"m")+1),F8))
E9: =IF(A9="","",IFERROR(C9/B9,0)) | F9: =IF(A9="","",MAX(B9-C9,0)) | G9: =IF(OR(A9="",D9=""),"",IFERROR(F9/(DATEDIF(TODAY(),D9,"m")+1),F9))
E10: =IF(A10="","",IFERROR(C10/B10,0)) | F10: =IF(A10="","",MAX(B10-C10,0)) | G10: =IF(OR(A10="",D10=""),"",IFERROR(F10/(DATEDIF(TODAY(),D10,"m")+1),F10))
E11: =IF(A11="","",IFERROR(C11/B11,0)) | F11: =IF(A11="","",MAX(B11-C11,0)) | G11: =IF(OR(A11="",D11=""),"",IFERROR(F11/(DATEDIF(TODAY(),D11,"m")+1),F11))
E12: =IF(A12="","",IFERROR(C12/B12,0)) | F12: =IF(A12="","",MAX(B12-C12,0)) | G12: =IF(OR(A12="",D12=""),"",IFERROR(F12/(DATEDIF(TODAY(),D12,"m")+1),F12))
E13: =IF(A13="","",IFERROR(C13/B13,0)) | F13: =IF(A13="","",MAX(B13-C13,0)) | G13: =IF(OR(A13="",D13=""),"",IFERROR(F13/(DATEDIF(TODAY(),D13,"m")+1),F13))
... E401: =IF(A401="","",IFERROR(C401/B401,0)) | F401: =IF(A401="","",MAX(B401-C401,0)) | G401: =IF(OR(A401="",D401=""),"",IFERROR(F401/(DATEDIF(TODAY(),D401,"m")+1),F401))

Sheet Tareas
A1: Tarea | B1: Prioridad | C1: Vence | D1: Estado | E1: Hecha el | F1: Creada

Sheet Recurrentes
A1: Pago | B1: Monto (S/) | C1: Categoría | D1: Día del mes | E1: Activo

Sheet Recordatorios
A1: Recordatorio | B1: Próxima vez | C1: Se repite
